{"data": [{"begin_time": 1583164800, "bid_avg": "0.40", "bill_second_bid_avg": "2.50", "budget": 100000, "clk_pv": 1, "clk_target_f_pv": 0, "clk_target_t_pv": 1, "clk_uv": 1, "comindex": 0, "contract_flag": 2, "conv_index": 0, "conv_index_cpa": "--", "conv_index_cpa_target_f": "--", "conv_index_cpa_target_t": "--", "conv_index_cvr": "0.0000", "conv_index_cvr_target_f": "--", "conv_index_cvr_target_t": "0.0000", "conv_index_target_f": 0, "conv_index_target_t": 0, "cpc": "0.00", "cpc_target_f": "--", "cpc_target_t": "0.00", "ctr": "0.5000", "ctr_target_f": "--", "ctr_target_t": "0.5000", "date": "20200614", "ecpm": "0.00", "end_time": 1585756799, "exp_pv": 2, "exp_pv_avg": "2.00", "exp_target_f_pv": 0, "exp_target_t_pv": 2, "exp_uv": 1, "id": "227200282", "income_from_minigame_reg_arpu": "--", "minigame_realization_roi_first_pv": 0, "multi_slot_type": 0, "name": "保皇MP52064", "paid": "0.00", "paid_target_f": "0.00", "paid_target_t": "0.00", "pos_type": 7, "product_type": "PRODUCTTYPE_WECHAT_MINI_GAME", "second_ocpm_comindex": 0, "second_ocpm_comindex_target_f": 0, "second_ocpm_comindex_target_t": 0, "second_ocpm_cpa": "--", "second_ocpm_cpa_target_f": "--", "second_ocpm_cpa_target_t": "--", "second_ocpm_cvr": "0.0000", "second_ocpm_cvr_target_f": "--", "second_ocpm_cvr_target_t": "0.0000", "status": "ADSTATUS_FINISH", "weapp_purchase_all_dedup_pv": 0, "weapp_purchase_amount": "0.00", "weapp_purchase_amount_roi": "--", "weapp_purchase_firstday_amount": "0.00", "weapp_purchase_firstday_pv": 0, "weapp_purchase_pv": 0, "weapp_reg_cost": "--", "weapp_reg_pv": 0, "weapp_reg_rate": "0.0000", "weapp_start_pv": 0}], "ret": 0, "ret_msg": "ok", "select_conf": {"total_num": 1, "update_minute": "202006142259"}, "total": {"bid_avg": "0.40", "bill_second_bid_avg": "2.50", "canvas_cpn_coupons_get_pv": 0, "clk_pv": 1, "clk_target_f_pv": 0, "clk_target_t_pv": 1, "clk_uv": 1, "comindex": 0, "conv_index": 0, "conv_index_cpa": "--", "conv_index_cpa_target_f": "--", "conv_index_cpa_target_t": "--", "conv_index_cvr": "0.0000", "conv_index_cvr_target_f": "--", "conv_index_cvr_target_t": "0.0000", "conv_index_target_f": 0, "conv_index_target_t": 0, "cpa": "--", "cpc": "0.00", "cpc_target_f": "--", "cpc_target_t": "0.00", "ctr": "0.5000", "ctr_target_f": "--", "ctr_target_t": "0.5000", "ecpm": "0.00", "exp_pv": 2, "exp_pv_avg": "2.00", "exp_target_f_pv": 0, "exp_target_t_pv": 2, "exp_uv": 1, "income_from_minigame_reg_arpu": "--", "minigame_realization_roi_first_pv": 0, "ocpm_comindex": 0, "ocpm_comindex_target_f": 0, "ocpm_comindex_target_t": 0, "ocpm_cpa": "--", "ocpm_cpa_target_f": "--", "ocpm_cpa_target_t": "--", "paid": "0.00", "paid_target_f": "0.00", "paid_target_t": "0.00", "second_ocpm_comindex": 0, "second_ocpm_comindex_target_f": 0, "second_ocpm_comindex_target_t": 0, "second_ocpm_cpa": "--", "second_ocpm_cpa_target_f": "--", "second_ocpm_cpa_target_t": "--", "second_ocpm_cvr": "0.0000", "second_ocpm_cvr_target_f": "--", "second_ocpm_cvr_target_t": "0.0000", "weapp_purchase_all_dedup_pv": 0, "weapp_purchase_amount": "0.00", "weapp_purchase_amount_roi": "--", "weapp_purchase_firstday_amount": "0.00", "weapp_purchase_firstday_pv": 0, "weapp_purchase_pv": 0, "weapp_reg_cost": "--", "weapp_reg_pv": 0, "weapp_reg_rate": "0.0000", "weapp_start_pv": 0}, "appid": "wx72aa3bddeee260be"}